setup.py
PowerFullSoap/Soap.py
PowerFullSoap/__init__.py
PowerFullSoap.egg-info/PKG-INFO
PowerFullSoap.egg-info/SOURCES.txt
PowerFullSoap.egg-info/dependency_links.txt
PowerFullSoap.egg-info/requires.txt
PowerFullSoap.egg-info/top_level.txt