Metadata-Version: 1.1
Name: PowerFullSoap
Version: 0.3.1
Summary: PowerFullSoap
Home-page: UNKNOWN
Author: ahmetatakan
Author-email: ahmetatakan79@gmail.com
License: UNKNOWN
Platform: UNKNOWN
Classifier: Intended Audience :: Developers
Classifier: License :: OSI Approved :: BSD License
Classifier: Operating System :: OS Independent
Classifier: Programming Language :: Python
Classifier: Programming Language :: Python :: 3.5
Classifier: Programming Language :: Python :: 3.6
Classifier: Topic :: Internet :: WWW/HTTP
Classifier: Topic :: Internet :: WWW/HTTP :: Dynamic Content
